atikin_click/__init__.py
atikin_click/__main__.py
atikin_click/async_hello.py
atikin_click/autocomplete.py
atikin_click/cli.py
atikin_click/completion.py
atikin_click/config.py
atikin_click/logging.py
atikin_click/output.py
atikin_click/plugins.py
atikin_click/progress.py
atikin_click/prompts.py
atikin_click/repl.py
atikin_click/sample_plugin.py
atikin_click/testing.py
atikin_click/tui.py
atikin_click/validators.py
atikin_click-0.0.1.dist-info/licenses/LICENSE
atikin_click-0.0.1.dist-info/METADATA
atikin_click-0.0.1.dist-info/WHEEL
atikin_click-0.0.1.dist-info/entry_points.txt
atikin_click-0.0.1.dist-info/top_level.txt
atikin_click-0.0.1.dist-info/RECORD
