Metadata-Version: 2.4
Name: atikin_click
Version: 0.0.1
Summary: Atikin-Click — lightweight developer-friendly CLI toolkit (autocomplete, colored output, progress & spinners).
Author-email: Atikin Verse <atikinverse@gmail.com>
License: MIT
Keywords: cli,Atikin-Verse,Atikin,Verse,Atikin-Tools,command-line,command-line-tool,developer,productivity,automation,tools,utilities,shell,terminal,progress,spinner,progress-bar,interactive,script,plugin,plugins,autocomplete,bash,zsh,fish,python-cli,python-toolkit,rich,output,color,colored,developer-tool,lightweight
Classifier: Programming Language :: Python :: 3
Classifier: License :: OSI Approved :: MIT License
Classifier: Development Status :: 4 - Beta
Classifier: Intended Audience :: Developers
Requires-Python: >=3.8
License-File: LICENSE
Provides-Extra: dev
Requires-Dist: pytest>=7.0; extra == "dev"
Dynamic: license-file
Dynamic: requires-python
